rhinopics/__init__.py
rhinopics/__main__.py
rhinopics/_version.py
rhinopics/rhinobuilder.py
rhinopics/rhinofile.py
rhinopics/rhinopic.py
rhinopics/rhinovid.py
rhinopics-0.2.5.dist-info/licenses/LICENSE
rhinopics-0.2.5.dist-info/METADATA
rhinopics-0.2.5.dist-info/WHEEL
rhinopics-0.2.5.dist-info/entry_points.txt
rhinopics-0.2.5.dist-info/top_level.txt
rhinopics-0.2.5.dist-info/RECORD
