Metadata-Version: 2.4
Name: rhinopics
Version: 0.2.5
Summary: Rhinopics, let the fat unicorn rename yours pics!
Home-page: https://github.com/axelfahy/rhinopics
Download-URL: 
Author-email: Axel Fahy <axel@fahy.net>
Maintainer: Axel Fahy
Maintainer-email: Axel Fahy <axel@fahy.net>
License: MIT License
Project-URL: Homepage, https://github.com/axelfahy/rhinopics
Project-URL: Repository, https://github.com/axelfahy/rhinopics
Project-URL: Issues, https://github.com/axelfahy/rhinopics/issues
Project-URL: Changelog, https://github.com/axelfahy/rhinopics/CHANGELOG.md
Keywords: pictures,photos,renaming
Classifier: Development Status :: 3 - Alpha
Classifier: Environment :: Console
Classifier: Intended Audience :: End Users/Desktop
Classifier: Programming Language :: Python :: 3
Classifier: Programming Language :: Python :: 3.8
Classifier: Programming Language :: Python :: 3.9
Classifier: Programming Language :: Python :: 3.10
Classifier: Programming Language :: Python :: 3.11
Classifier: Programming Language :: Python :: 3.12
Classifier: Programming Language :: Python :: 3.13
Classifier: Programming Language :: Python :: 3.14
Classifier: Topic :: Multimedia
Classifier: Topic :: Utilities
Requires-Python: >=3.10
License-File: LICENSE
Requires-Dist: click==8.3.1
Requires-Dist: click-pathlib==2020.3.13.0
Requires-Dist: exifread
Requires-Dist: ffmpeg-python==0.2.0
Requires-Dist: python-dateutil==2.9.0
Requires-Dist: tqdm==4.67.1
Dynamic: home-page
Dynamic: license-file
Dynamic: maintainer
Dynamic: requires-python
